bahiart_gym/__init__.py
bahiart_gym/agentcomms.py
bahiart_gym/start.py
bahiart_gym/terminate.py
bahiart_gym/envs/__init__.py
bahiart_gym/envs/demo_env.py
bahiart_gym/server/__init__.py
bahiart_gym/server/abstfilter.py
bahiart_gym/server/agentParser.py
bahiart_gym/server/agentProxy.py
bahiart_gym/server/ball.py
bahiart_gym/server/comms.py
bahiart_gym/server/parsr.py
bahiart_gym/server/player.py
bahiart_gym/server/proxy.py
bahiart_gym/server/serverParser.py
bahiart_gym/server/sexpr.py
bahiart_gym/server/singleton.py
bahiart_gym/server/trainer.py
bahiart_gym/server/world.py
bahiart_gym-1.0.5.dist-info/COPYING.md
bahiart_gym-1.0.5.dist-info/LICENSE.md
bahiart_gym-1.0.5.dist-info/METADATA
bahiart_gym-1.0.5.dist-info/WHEEL
bahiart_gym-1.0.5.dist-info/top_level.txt
bahiart_gym-1.0.5.dist-info/RECORD
