Metadata-Version: 2.1
Name: bahiart-gym
Version: 1.0.5
Summary: A toolkit to develop openAI Gym environments on top of the RCSSSERVER3D simulator
Home-page: https://bitbucket.org/bahiart3d/bahiart-gym/
Author: Gabriel Mascarenhas, Marco A. C. Simões, Rafael Fonseca
Author-email: teambahiart@gmail.com
License: agpl-3.0
Keywords: CUSTOM,ENVIRONMENT,GYM,OPTIMIZATION,MACHINE,LEARNING
Classifier: Development Status :: 5 - Production/Stable
Classifier: Intended Audience :: Developers
Classifier: Intended Audience :: Science/Research
Classifier: Topic :: Software Development :: Build Tools
Classifier: License :: OSI Approved :: GNU Affero General Public License v3
Classifier: Programming Language :: Python :: 3.7
Classifier: Topic :: Scientific/Engineering :: Artificial Intelligence
License-File: LICENSE.md
License-File: COPYING.md
Requires-Dist: gym
Requires-Dist: numpy
